lbr_trex_client/__init__.py
lbr_trex_client/external_libs/dpkt-1.9.1/dpkt/__init__.py
lbr_trex_client/external_libs/dpkt-1.9.1/dpkt/ah.py
lbr_trex_client/external_libs/dpkt-1.9.1/dpkt/aim.py
lbr_trex_client/external_libs/dpkt-1.9.1/dpkt/aoe.py
lbr_trex_client/external_libs/dpkt-1.9.1/dpkt/aoeata.py
lbr_trex_client/external_libs/dpkt-1.9.1/dpkt/aoecfg.py
lbr_trex_client/external_libs/dpkt-1.9.1/dpkt/arp.py
lbr_trex_client/external_libs/dpkt-1.9.1/dpkt/asn1.py
lbr_trex_client/external_libs/dpkt-1.9.1/dpkt/bgp.py
lbr_trex_client/external_libs/dpkt-1.9.1/dpkt/cdp.py
lbr_trex_client/external_libs/dpkt-1.9.1/dpkt/compat.py
lbr_trex_client/external_libs/dpkt-1.9.1/dpkt/crc32c.py
lbr_trex_client/external_libs/dpkt-1.9.1/dpkt/decorators.py
lbr_trex_client/external_libs/dpkt-1.9.1/dpkt/dhcp.py
lbr_trex_client/external_libs/dpkt-1.9.1/dpkt/diameter.py
lbr_trex_client/external_libs/dpkt-1.9.1/dpkt/dns.py
lbr_trex_client/external_libs/dpkt-1.9.1/dpkt/dpkt.py
lbr_trex_client/external_libs/dpkt-1.9.1/dpkt/dtp.py
lbr_trex_client/external_libs/dpkt-1.9.1/dpkt/edp.py
lbr_trex_client/external_libs/dpkt-1.9.1/dpkt/esp.py
lbr_trex_client/external_libs/dpkt-1.9.1/dpkt/ethernet.py
lbr_trex_client/external_libs/dpkt-1.9.1/dpkt/gre.py
lbr_trex_client/external_libs/dpkt-1.9.1/dpkt/gzip.py
lbr_trex_client/external_libs/dpkt-1.9.1/dpkt/h225.py
lbr_trex_client/external_libs/dpkt-1.9.1/dpkt/hsrp.py
lbr_trex_client/external_libs/dpkt-1.9.1/dpkt/http.py
lbr_trex_client/external_libs/dpkt-1.9.1/dpkt/http2.py
lbr_trex_client/external_libs/dpkt-1.9.1/dpkt/icmp.py
lbr_trex_client/external_libs/dpkt-1.9.1/dpkt/icmp6.py
lbr_trex_client/external_libs/dpkt-1.9.1/dpkt/ieee80211.py
lbr_trex_client/external_libs/dpkt-1.9.1/dpkt/igmp.py
lbr_trex_client/external_libs/dpkt-1.9.1/dpkt/ip.py
lbr_trex_client/external_libs/dpkt-1.9.1/dpkt/ip6.py
lbr_trex_client/external_libs/dpkt-1.9.1/dpkt/ipip.py
lbr_trex_client/external_libs/dpkt-1.9.1/dpkt/ipx.py
lbr_trex_client/external_libs/dpkt-1.9.1/dpkt/llc.py
lbr_trex_client-3.4.0.dist-info/LICENSE
lbr_trex_client-3.4.0.dist-info/METADATA
lbr_trex_client-3.4.0.dist-info/WHEEL
lbr_trex_client-3.4.0.dist-info/top_level.txt
lbr_trex_client-3.4.0.dist-info/RECORD
