Metadata-Version: 2.1
Name: lbr_trex_client
Version: 3.4.0
Summary: Lbr-trex-client package contains TRex traffic generator client API as Python package.
Author-email: CESNET <tmc-info@cesnet.cz>
Maintainer-email: Dominik Tran <tran@cesnet.cz>
License: Apache 2.0 with Scapy having GPLv2. Inherited from TRex. See https://github.com/cisco-system-traffic-generator/trex-core/blob/master/LICENSE and https://github.com/cisco-system-traffic-generator/trex-core/blob/master/LICENSE_Python_Client
Project-URL: repository, https://github.com/CESNET/lbr-trex-client
Classifier: Programming Language :: Python :: 3.8
Requires-Python: >=3.8
License-File: LICENSE
